ridgeplot/__init__.py
ridgeplot/colors.py
ridgeplot/dotted_heatmap.py
ridgeplot/ridge_plot.py
ridgeplot/stats.py
ridgeplot_py-0.6.4.dist-info/METADATA
ridgeplot_py-0.6.4.dist-info/WHEEL
ridgeplot_py-0.6.4.dist-info/licenses/LICENSE
ridgeplot_py-0.6.4.dist-info/RECORD
