Metadata-Version: 2.3
Name: ridgeplot-py
Version: 0.6.4
Summary: Plotting ridgeplots with matplotlib
Author-email: Douglas Wu <wckdouglas@gmail.com>
License: MIT
Requires-Python: >=3.9
Requires-Dist: matplotlib>=3.8
Requires-Dist: more-itertools>=8.9.0
Requires-Dist: numpy>=1.21.1
Requires-Dist: pandas>=2.2.2
Requires-Dist: scipy>=1.8.0
